{
	"format_version": "1.12.0",
	"minecraft:geometry": [
		{
			"description": {
				"identifier": "geometry.scifi_tentacle",
				"texture_width": 64,
				"texture_height": 64,
				"visible_bounds_width": 4,
				"visible_bounds_height": 3.5,
				"visible_bounds_offset": [0, 1.25, 0]
			},
			"bones": [
				{
					"name": "root",
					"pivot": [0, 0, 0]
				},
				{
					"name": "waist",
					"parent": "root",
					"pivot": [0, 12, 0]
				},
				{
					"name": "body",
					"parent": "waist",
					"pivot": [0, 12, 0],
					"cubes": [
						{
							"origin": [-4, 12, -2],
							"size": [8, 12, 4],
							"uv": {
								"north": {"uv": [0, 52], "uv_size": [8, 12]},
								"east": {"uv": [0, 48], "uv_size": [4, 12]},
								"south": {"uv": [28, 49], "uv_size": [8, 12]},
								"west": {"uv": [1, 49], "uv_size": [4, 12]},
								"up": {"uv": [33, 50], "uv_size": [8, 4]},
								"down": {"uv": [0, 58], "uv_size": [8, -4]}
							}
						},
						{
							"origin": [-4, 12, -2],
							"size": [8, 12, 4],
							"inflate": 0.25,
							"uv": {
								"north": {"uv": [40, 56], "uv_size": [12, 8]},
								"east": {"uv": [6, 51], "uv_size": [4, 12]},
								"south": {"uv": [0, 52], "uv_size": [8, 12]},
								"west": {"uv": [4, 52], "uv_size": [4, 12]},
								"up": {"uv": [0, 60], "uv_size": [8, 4]},
								"down": {"uv": [0, 62], "uv_size": [8, -4]}
							}
						}
					]
				},
				{
					"name": "rightArm",
					"parent": "body",
					"pivot": [-5, 22, 0],
					"cubes": [
						{
							"origin": [-8, 12, -2],
							"size": [4, 12, 4],
							"uv": {
								"north": {"uv": [60, 21], "uv_size": [4, 12]},
								"east": {"uv": [58, 34], "uv_size": [4, 12]},
								"south": {"uv": [59, 21], "uv_size": [4, 12]},
								"west": {"uv": [60, 20], "uv_size": [4, 12]},
								"up": {"uv": [58, 17], "uv_size": [4, 4]},
								"down": {"uv": [59, 20], "uv_size": [4, -4]}
							}
						},
						{
							"origin": [-8, 12, -2],
							"size": [4, 12, 4],
							"inflate": 0.25,
							"uv": {
								"north": {"uv": [37, 52], "uv_size": [4, 12]},
								"east": {"uv": [38, 52], "uv_size": [4, 12]},
								"south": {"uv": [38, 52], "uv_size": [4, 12]},
								"west": {"uv": [39, 52], "uv_size": [4, 12]},
								"up": {"uv": [37, 60], "uv_size": [4, 4]},
								"down": {"uv": [39, 64], "uv_size": [4, -4]}
							}
						}
					]
				},
				{
					"name": "right_item",
					"parent": "rightArm",
					"pivot": [-5, 22, 0]
				},
				{
					"name": "leftArm",
					"parent": "body",
					"pivot": [5, 22, 0],
					"cubes": [
						{
							"origin": [4, 12, -2],
							"size": [4, 12, 4],
							"uv": {
								"north": {"uv": [36, 52], "uv_size": [4, 12]},
								"east": {"uv": [32, 52], "uv_size": [4, 12]},
								"south": {"uv": [44, 52], "uv_size": [4, 12]},
								"west": {"uv": [40, 52], "uv_size": [4, 12]},
								"up": {"uv": [36, 48], "uv_size": [4, 4]},
								"down": {"uv": [40, 52], "uv_size": [4, -4]}
							}
						},
						{
							"origin": [4, 12, -2],
							"size": [4, 12, 4],
							"inflate": 0.25,
							"uv": {
								"north": {"uv": [57, 52], "uv_size": [4, 12]},
								"east": {"uv": [48, 52], "uv_size": [4, 12]},
								"south": {"uv": [57, 52], "uv_size": [4, 12]},
								"west": {"uv": [56, 52], "uv_size": [4, 12]},
								"up": {"uv": [57, 58], "uv_size": [4, 4]},
								"down": {"uv": [56, 64], "uv_size": [4, -4]}
							}
						}
					]
				},
				{
					"name": "head",
					"parent": "body",
					"pivot": [0, 24, 0]
				},
				{
					"name": "bone",
					"parent": "body",
					"pivot": [0.16667, 19, 4.83333],
					"rotation": [0, 90, -45]
				},
				{
					"name": "bone2",
					"parent": "bone",
					"pivot": [0.5, 20.2132, 5.08579],
					"cubes": [
						{"origin": [-2, 19.2132, 2.58579], "size": [3, 10, 3], "uv": [30, 0]},
						{"origin": [2.5, 29.2132, 3.08579], "size": [2, 10, 2], "pivot": [0.5, 38.4632, 3.08579], "rotation": [0, 0, 22.5], "uv": [23, 35]},
						{"origin": [8.32192, 38.10896, 1.08579], "size": [0, 7, 4], "pivot": [5.82192, 40.85896, 3.08579], "rotation": [0, 0, 67.5], "uv": [14, 11]}
					]
				},
				{
					"name": "bone6",
					"parent": "bone",
					"pivot": [0.5, 20.7132, 4.58579],
					"cubes": [
						{"origin": [-2.92491, 10.21912, -3.47102], "size": [3, 10, 3], "pivot": [3.48577, 20.21103, -7.72792], "rotation": [67.28507, 12.31064, -24.78507], "uv": [11, 27]},
						{"origin": [3.2045, 18.40408, -14.47981], "size": [2, 10, 2], "pivot": [-0.37464, 26.70752, -12.00125], "rotation": [67.4854, -39.90501, 16.49631], "uv": [0, 29]},
						{"origin": [2.39588, 31.57708, -16.47981], "size": [0, 7, 4], "pivot": [-0.37464, 26.70752, -12.00125], "rotation": [9.17887, -72.68946, 81.99863], "uv": [0, 9]}
					]
				},
				{
					"name": "bone4",
					"parent": "bone",
					"pivot": [-0.5, 17.7132, 0.58579],
					"cubes": [
						{"origin": [-2, 16.2132, 0.58579], "size": [3, 3, 10], "uv": [0, 0]},
						{"origin": [2.5, 16.7132, 10.58579], "size": [2, 2, 10], "pivot": [0.5, 18.7132, 19.83579], "rotation": [0, 22.5, 0], "uv": [16, 3]},
						{"origin": [8.32192, 16.7132, 19.48154], "size": [0, 4, 7], "pivot": [5.82192, 18.7132, 22.23154], "rotation": [0, 67.5, 0], "uv": [23, 24]}
					]
				},
				{
					"name": "bone3",
					"parent": "bone",
					"pivot": [1, 19.2132, 5.58579],
					"cubes": [
						{"origin": [-3.70587, 22.12672, 5.74173], "size": [2, 2, 10], "pivot": [3.55839, 24.93072, 10.76754], "rotation": [50.4332, -35.58091, -18.95331], "uv": [14, 15]},
						{"origin": [-3.65616, 22.12672, 10.28731], "size": [0, 4, 7], "pivot": [3.55839, 24.93072, 10.76754], "rotation": [38.8728, -2.58575, 14.11591], "uv": [23, 20]}
					]
				},
				{
					"name": "bone5",
					"parent": "bone",
					"pivot": [2, 19.2132, 3.58579],
					"cubes": [
						{"origin": [5.14777, 18.73267, 13.26798], "size": [2, 2, 10], "pivot": [-2.44161, 24.93072, 10.76754], "rotation": [-94.49666, 14.58148, 32.13118], "uv": [0, 13]},
						{"origin": [-4.47492, 18.73267, 26.11228], "size": [0, 4, 7], "pivot": [-2.44161, 24.93072, 10.76754], "rotation": [-103.50226, 7.14418, -13.14003], "uv": [0, 18]}
					]
				},
				{
					"name": "leftLeg",
					"parent": "waist",
					"pivot": [1.9, 12, 0],
					"cubes": [
						{
							"origin": [-0.1, 0, -2],
							"size": [4, 12, 4],
							"uv": {
								"north": {"uv": [29, 52], "uv_size": [4, 12]},
								"east": {"uv": [30, 51], "uv_size": [4, 12]},
								"south": {"uv": [28, 52], "uv_size": [4, 12]},
								"west": {"uv": [24, 52], "uv_size": [4, 12]},
								"up": {"uv": [20, 48], "uv_size": [4, 4]},
								"down": {"uv": [24, 52], "uv_size": [4, -4]}
							}
						},
						{
							"origin": [-0.1, 0, -2],
							"size": [4, 12, 4],
							"inflate": 0.25,
							"uv": {
								"north": {"uv": [4, 52], "uv_size": [4, 12]},
								"east": {"uv": [0, 52], "uv_size": [4, 12]},
								"south": {"uv": [1, 52], "uv_size": [4, 12]},
								"west": {"uv": [2, 52], "uv_size": [4, 12]},
								"up": {"uv": [4, 48], "uv_size": [4, 4]},
								"down": {"uv": [8, 52], "uv_size": [4, -4]}
							}
						}
					]
				},
				{
					"name": "rightLeg",
					"parent": "waist",
					"pivot": [-1.9, 12, 0],
					"cubes": [
						{
							"origin": [-3.9, 0, -2],
							"size": [4, 12, 4],
							"uv": {
								"north": {"uv": [36, 52], "uv_size": [4, 12]},
								"east": {"uv": [32, 52], "uv_size": [4, 12]},
								"south": {"uv": [44, 52], "uv_size": [4, 12]},
								"west": {"uv": [40, 52], "uv_size": [4, 12]},
								"up": {"uv": [36, 48], "uv_size": [4, 4]},
								"down": {"uv": [40, 52], "uv_size": [4, -4]}
							}
						},
						{
							"origin": [-3.9, 0, -2],
							"size": [4, 12, 4],
							"inflate": 0.25,
							"uv": {
								"north": {"uv": [49, 50], "uv_size": [4, 12]},
								"east": {"uv": [44, 44], "uv_size": [4, 12]},
								"south": {"uv": [23, 46], "uv_size": [4, 12]},
								"west": {"uv": [0, 52], "uv_size": [4, 12]},
								"up": {"uv": [4, 48], "uv_size": [4, 4]},
								"down": {"uv": [5, 56], "uv_size": [4, -4]}
							}
						}
					]
				}
			]
		}
	]
}